django_autoapi/README.md
django_autoapi/__init__.py
django_autoapi/apps.py
django_autoapi/core.py
django_autoapi/decorators.py
django_autoapi/examples.py
django_autoapi/metaclass.py
django_autoapi/registry.py
django_autoapi/routers.py
django_autoapi/urls.py
django_autoapi/utils.py
django_autoapi/examples/advanced_features_demo.py
django_autoapi/examples/integration_test.py
django_autoapi/examples/multiple_apis_per_model.py
django_autoapi/examples/test_custom_endpoints_demo.py
django_autoapi/factories/__init__.py
django_autoapi/factories/serializer.py
django_autoapi/factories/viewset.py
django_autoapi/filters/__init__.py
django_autoapi/filters/dynamic.py
django_autoapi/migrations/0001_initial.py
django_autoapi/migrations/__init__.py
django_autoapi/permissions/__init__.py
django_autoapi/permissions/base.py
django_autoapi/recordrules/__init__.py
django_autoapi/recordrules/admin.py
django_autoapi/recordrules/engine.py
django_autoapi/recordrules/examples.py
django_autoapi/recordrules/expressions.py
django_autoapi/recordrules/filters.py
django_autoapi/recordrules/logging.py
django_autoapi/recordrules/mixins.py
django_autoapi/recordrules/models.py
django_autoapi/recordrules/performance.py
django_autoapi/recordrules/registry.py
django_autoapi/tests/__init__.py
django_autoapi/tests/conftest.py
django_autoapi/tests/test_advanced_endpoints.py
django_autoapi/tests/test_advanced_features.py
django_autoapi/tests/test_complete_integration.py
django_autoapi/tests/test_core.py
django_autoapi/tests/test_custom_endpoints.py
django_autoapi/tests/test_custom_endpoints_integration.py
django_autoapi/tests/test_decorators.py
django_autoapi/tests/test_edge_cases.py
django_autoapi/tests/test_enhanced_serializer.py
django_autoapi/tests/test_integration.py
django_autoapi/tests/test_metaclass.py
django_autoapi/tests/test_recordrules_advanced.py
django_autoapi/tests/test_recordrules_engine.py
django_autoapi/tests/test_recordrules_integration.py
django_autoapi/tests/test_recordrules_models.py
django_autoapi_framework-1.0.0.dist-info/licenses/LICENSE
django_autoapi_framework-1.0.0.dist-info/METADATA
django_autoapi_framework-1.0.0.dist-info/WHEEL
django_autoapi_framework-1.0.0.dist-info/top_level.txt
django_autoapi_framework-1.0.0.dist-info/RECORD
