Metadata-Version: 2.4
Name: django-autoapi-framework
Version: 1.0.0
Summary: Zero-boilerplate REST APIs for Django with row-level security
Home-page: https://github.com/nakula-academy/django-autoapi
Author: Backend Development Team
Author-email: Backend Development Team <dev@example.com>
Maintainer: Backend Development Team
Maintainer-email: Backend Development Team <dev@example.com>
License: MIT
Project-URL: Homepage, https://github.com/nakula-academy/django-autoapi
Project-URL: Documentation, https://github.com/nakula-academy/django-autoapi#readme
Project-URL: Repository, https://github.com/nakula-academy/django-autoapi
Project-URL: Bug Tracker, https://github.com/nakula-academy/django-autoapi/issues
Project-URL: Changelog, https://github.com/nakula-academy/django-autoapi/blob/main/CHANGELOG.md
Keywords: django,rest-api,crud,autoapi,record-rules,row-level-security,permissions,django-rest-framework,drf,api-framework,rapid-development
Classifier: Development Status :: 5 - Production/Stable
Classifier: Environment :: Web Environment
Classifier: Framework :: Django
Classifier: Framework :: Django :: 4.2
Classifier: Framework :: Django :: 5.0
Classifier: Framework :: Django :: 5.1
Classifier: Intended Audience :: Developers
Classifier: Intended Audience :: System Administrators
Classifier: License :: OSI Approved :: MIT License
Classifier: Natural Language :: English
Classifier: Natural Language :: Indonesian
Classifier: Operating System :: OS Independent
Classifier: Programming Language :: Python :: 3
Classifier: Programming Language :: Python :: 3.8
Classifier: Programming Language :: Python :: 3.9
Classifier: Programming Language :: Python :: 3.10
Classifier: Programming Language :: Python :: 3.11
Classifier: Programming Language :: Python :: 3.12
Classifier: Programming Language :: Python :: 3 :: Only
Classifier: Topic :: Database
Classifier: Topic :: Internet :: WWW/HTTP
Classifier: Topic :: Internet :: WWW/HTTP :: Dynamic Content
Classifier: Topic :: Software Development :: Code Generators
Classifier: Topic :: Software Development :: Libraries :: Application Frameworks
Classifier: Topic :: Software Development :: Libraries :: Python Modules
Requires-Python: >=3.8
License-File: LICENSE
Requires-Dist: Django>=4.2
Requires-Dist: djangorestframework>=3.14
Requires-Dist: django-filter>=23.0
Provides-Extra: dev
Requires-Dist: pytest>=7.0; extra == "dev"
Requires-Dist: pytest-django>=4.5; extra == "dev"
Requires-Dist: pytest-cov>=4.0; extra == "dev"
Requires-Dist: black>=23.0; extra == "dev"
Requires-Dist: flake8>=6.0; extra == "dev"
Requires-Dist: isort>=5.0; extra == "dev"
Requires-Dist: mypy>=1.0; extra == "dev"
Requires-Dist: django-stubs>=4.2; extra == "dev"
Provides-Extra: docs
Requires-Dist: mkdocs>=1.5; extra == "docs"
Requires-Dist: mkdocs-material>=9.0; extra == "docs"
Requires-Dist: mkdocstrings>=0.24; extra == "docs"
Requires-Dist: mkdocstrings-python>=0.10; extra == "docs"
Provides-Extra: test
Requires-Dist: pytest>=7.0; extra == "test"
Requires-Dist: pytest-django>=4.5; extra == "test"
Requires-Dist: pytest-cov>=4.0; extra == "test"
Requires-Dist: factory-boy>=3.3; extra == "test"
Provides-Extra: all
Requires-Dist: pytest>=7.0; extra == "all"
Requires-Dist: pytest-django>=4.5; extra == "all"
Requires-Dist: pytest-cov>=4.0; extra == "all"
Requires-Dist: black>=23.0; extra == "all"
Requires-Dist: flake8>=6.0; extra == "all"
Requires-Dist: isort>=5.0; extra == "all"
Requires-Dist: mypy>=1.0; extra == "all"
Requires-Dist: django-stubs>=4.2; extra == "all"
Requires-Dist: mkdocs>=1.5; extra == "all"
Requires-Dist: mkdocs-material>=9.0; extra == "all"
Requires-Dist: mkdocstrings>=0.24; extra == "all"
Requires-Dist: mkdocstrings-python>=0.10; extra == "all"
Dynamic: author
Dynamic: home-page
Dynamic: license-file
Dynamic: maintainer
Dynamic: requires-python
